README.md
setup.py
blih_api/__init__.py
blih_api/__main__.py
blih_api/consts.py
blih_api/exceptions.py
blih_api.egg-info/PKG-INFO
blih_api.egg-info/SOURCES.txt
blih_api.egg-info/dependency_links.txt
blih_api.egg-info/entry_points.txt
blih_api.egg-info/requires.txt
blih_api.egg-info/top_level.txt