Metadata-Version: 1.0
Name: blih-api
Version: 0.0.4
Summary: Blih API - Epitech Blih Library
Home-page: https://github.com/SakiiR/blih-api
Author: SakiiR SakiiR (@SakiiR)
Author-email: UNKNOWN
License: UNKNOWN
Platform: UNKNOWN
